rtl/mem_shim.sv
module mem_shim (
    input             clk,
    input             rst_n,

    // MPEG2 Core memory request FIFO (read side) — clocked on clk (mem_clk)
    input       [1:0] mem_req_rd_cmd,
    input      [21:0] mem_req_rd_addr,
    input      [63:0] mem_req_rd_dta,
    output reg        mem_req_rd_en,
    input             mem_req_rd_valid,

    // MPEG2 Core memory response FIFO (write side) — clocked on clk (mem_clk)
    output reg [63:0] mem_res_wr_dta,
    output reg        mem_res_wr_en,
    input             mem_res_wr_almost_full,

    // DDR3 Controller Interface (Avalon-MM 64-bit)
    output     [28:0] ddr3_addr,
    output      [7:0] ddr3_burstcnt,
    output            ddr3_read,
    output            ddr3_write,
    output     [63:0] ddr3_writedata,
    output      [7:0] ddr3_byteenable,
    input      [63:0] ddr3_readdata,
    input             ddr3_readdatavalid,
    input             ddr3_waitrequest,

    // Debug outputs
    output     [3:0]  debug_state,
    output            debug_sdram_busy,
    output            debug_sdram_ack,
    output    [15:0]  debug_rd_count,
    output    [15:0]  debug_wr_count
);

    // Command encoding (from mem_codes.v)
    localparam CMD_NOOP    = 2'd0;
    localparam CMD_REFRESH = 2'd1;
    localparam CMD_READ    = 2'd2;
    localparam CMD_WRITE   = 2'd3;

    // =========================================================================
    // DDR3 Avalon-MM outputs
    // =========================================================================
    reg        ram_read;
    reg        ram_write;
    reg [28:0] ram_address;
    reg [63:0] ram_writedata;

    assign ddr3_read       = ram_read;
    assign ddr3_write      = ram_write;
    assign ddr3_addr       = ram_address;
    assign ddr3_writedata  = ram_writedata;
    assign ddr3_burstcnt   = 8'd1;
    assign ddr3_byteenable = 8'hFF;

    // =========================================================================
    // FSM
    // =========================================================================
    // state=0 (IDLE): Accept new FIFO commands
    // state=1 (WAIT): Wait for transaction acceptance (!waitrequest)

    reg state;

    always @(posedge clk) begin
        if (!rst_n) begin
            state         <= 0;
            ram_read      <= 0;
            ram_write     <= 0;
            ram_address   <= 0;
            ram_writedata <= 0;
            mem_req_rd_en <= 0;
            mem_res_wr_en <= 0;
            mem_res_wr_dta <= 0;
        end
        else begin
            // -----------------------------------------------------------------
            // Response Path (Always Active)
            // -----------------------------------------------------------------
            mem_res_wr_en <= ddr3_readdatavalid;
            if (ddr3_readdatavalid)
                mem_res_wr_dta <= ddr3_readdata;

            // -----------------------------------------------------------------
            // Command Path
            // -----------------------------------------------------------------
            if (!state) begin
                // IDLE State
                // Default: Keep popping if response FIFO has space
                mem_req_rd_en <= !mem_res_wr_almost_full;

                if (mem_req_rd_valid && !mem_res_wr_almost_full) begin
                    case (mem_req_rd_cmd)
                        CMD_WRITE: begin
                            ram_write     <= 1;
                            ram_address   <= {4'b0011, mem_req_rd_addr, 3'b000};
                            ram_writedata <= mem_req_rd_dta;
                            state         <= 1;     // Go to WAIT
                            mem_req_rd_en <= 0;     // Stop popping
                        end
                        CMD_READ: begin
                            ram_read      <= 1;
                            ram_address   <= {4'b0011, mem_req_rd_addr, 3'b000};
                            state         <= 1;     // Go to WAIT
                            mem_req_rd_en <= 0;     // Stop popping
                        end
                        // Ignore NOOP/REFRESH, keep popping
                        default: ;
                    endcase
                end
            end
            else begin
                // WAIT State
                if (!ddr3_waitrequest) begin
                    // Transaction Accepted
                    ram_read  <= 0;
                    ram_write <= 0;
                    state     <= 0; // Back to IDLE
                    
                    // Resume flow control (look ahead for next cycle)
                    mem_req_rd_en <= !mem_res_wr_almost_full;
                end
                // Else: Stay in WAIT, holding ram_read/write/addr/data stable
            end
        end
    end

    // =========================================================================
    // Debug
    // =========================================================================
    reg [15:0] rd_count;
    reg [15:0] wr_count;

    wire rd_accepted = ddr3_read  && !ddr3_waitrequest;
    wire wr_accepted = ddr3_write && !ddr3_waitrequest;

    always @(posedge clk) begin
        if (!rst_n) begin
            rd_count <= 0;
            wr_count <= 0;
        end else begin
            if (rd_accepted) rd_count <= rd_count + 1'd1;
            if (wr_accepted) wr_count <= wr_count + 1'd1;
        end
    end

    assign debug_state      = {3'b000, state};
    assign debug_sdram_busy = ddr3_waitrequest;
    assign debug_sdram_ack  = rd_accepted | wr_accepted;
    assign debug_rd_count   = rd_count;
    assign debug_wr_count   = wr_count;

endmodule

bench/iverilog/tb_mem_shim.sv
`timescale 1ns / 1ps

module tb_mem_shim;

    reg clk;
    reg rst_n;

    // Core Interface
    reg  [1:0] mem_req_rd_cmd;
    reg [21:0] mem_req_rd_addr;
    reg [63:0] mem_req_rd_dta;
    wire       mem_req_rd_en;
    reg        mem_req_rd_valid;

    wire [63:0] mem_res_wr_dta;
    wire        mem_res_wr_en;
    reg         mem_res_wr_almost_full;

    // DDR3 Interface
    wire [28:0] ddr3_addr;
    wire  [7:0] ddr3_burstcnt;
    wire        ddr3_read;
    wire        ddr3_write;
    wire [63:0] ddr3_writedata;
    wire  [7:0] ddr3_byteenable;
    reg  [63:0] ddr3_readdata;
    reg         ddr3_readdatavalid;
    reg         ddr3_waitrequest;

    // DUT
    mem_shim uut (
        .clk(clk),
        .rst_n(rst_n),
        .mem_req_rd_cmd(mem_req_rd_cmd),
        .mem_req_rd_addr(mem_req_rd_addr),
        .mem_req_rd_dta(mem_req_rd_dta),
        .mem_req_rd_en(mem_req_rd_en),
        .mem_req_rd_valid(mem_req_rd_valid),
        .mem_res_wr_dta(mem_res_wr_dta),
        .mem_res_wr_en(mem_res_wr_en),
        .mem_res_wr_almost_full(mem_res_wr_almost_full),
        .ddr3_addr(ddr3_addr),
        .ddr3_burstcnt(ddr3_burstcnt),
        .ddr3_read(ddr3_read),
        .ddr3_write(ddr3_write),
        .ddr3_writedata(ddr3_writedata),
        .ddr3_byteenable(ddr3_byteenable),
        .ddr3_readdata(ddr3_readdata),
        .ddr3_readdatavalid(ddr3_readdatavalid),
        .ddr3_waitrequest(ddr3_waitrequest)
    );

    // Clock Generation
    initial begin
        clk = 0;
        forever #5 clk = ~clk; // 100MHz
    end

    // Test Sequence
    initial begin
        $dumpfile("mem_shim.vcd");
        $dumpvars(0, tb_mem_shim);

        // Initialize Inputs
        rst_n = 0;
        mem_req_rd_cmd = 0;
        mem_req_rd_addr = 0;
        mem_req_rd_dta = 0;
        mem_req_rd_valid = 0;
        mem_res_wr_almost_full = 0;
        ddr3_readdata = 0;
        ddr3_readdatavalid = 0;
        ddr3_waitrequest = 0;

        // Reset
        #20 rst_n = 1;
        #20;

        // Test 1: Simple Write
        $display("Test 1: Simple Write");
        
        // Assert Write Request
        mem_req_rd_cmd = 2'd3; // CMD_WRITE
        mem_req_rd_addr = 22'h123456;
        mem_req_rd_dta = 64'hDEADBEEFCAFEBABE;
        mem_req_rd_valid = 1;

        // Wait for acceptance
        wait(mem_req_rd_en == 0); // FSM should deassert EN when accepting
        @(posedge clk);
        #1; // Wait for combinational logic to settle
        $display("Core Request Accepted");
        
        if (ddr3_write !== 1) $error("DDR3 Write not asserted");
        // Address Check: Expect {4'b0011, 22'h123456, 3'b000}
        // 4'b0011 = 3
        if (ddr3_addr !== {4'b0011, 22'h123456, 3'b000}) $error("DDR3 Address mismatch. Got: %h", ddr3_addr);
        if (ddr3_writedata !== 64'hDEADBEEFCAFEBABE) $error("DDR3 Data mismatch");

        mem_req_rd_valid = 0;
        #20;

        // Test 2: Simple Read
        $display("Test 2: Simple Read");
        
        mem_req_rd_cmd = 2'd2; // CMD_READ
        mem_req_rd_addr = 22'h1BCDEF; 
        mem_req_rd_valid = 1;

        wait(mem_req_rd_en == 0);
        @(posedge clk); 
        #1;
        if (ddr3_read !== 1) $error("DDR3 Read not asserted");
        // Address Check
        if (ddr3_addr !== {4'b0011, 22'h1BCDEF, 3'b000}) $error("DDR3 Address mismatch. Got: %h", ddr3_addr);

        // FSM should still be in WAIT (waitrequest=0) -> IDLE next cycle
        mem_req_rd_valid = 0;
        #20;

        // Simulate Memory Response
        ddr3_readdata = 64'h0123456789ABCDEF;
        ddr3_readdatavalid = 1;
        $display("Time: %t, Setting valid=1", $time);
        @(posedge clk);
        #1; 
        ddr3_readdatavalid = 0;
        
        $display("Time: %t, Checking. en_out=%b, data=%h", $time, mem_res_wr_en, mem_res_wr_dta);
        
        // Check Core Response
        if (mem_res_wr_en !== 1) $error("Core Response not asserted");
        if (mem_res_wr_dta !== 64'h0123456789ABCDEF) $error("Core Response Data mismatch");

        #20;

        // Test 3: Backpressure (Waitrequest)
        $display("Test 3: Backpressure");
        
        ddr3_waitrequest = 1;
        mem_req_rd_cmd = 2'd2; // READ
        mem_req_rd_valid = 1;
        
        // Wait for FIFO accept (en=1 -> en=0)
        // With previous Waitrequest issue, en stayed 1 and read stayed 0.
        // Now read should go 1 and en should go 0.
        wait(mem_req_rd_en == 0);
        
        @(posedge clk);
        #1;
        
        // FSM should have transitioned to WAIT state and asserted READ
        if (ddr3_read !== 1) $error("DDR3 Read not asserted during Waitrequest");
        
        // Check if en became 0 (stall)
        if (mem_req_rd_en !== 0) $display("WARNING: mem_req_rd_en should be 0 in WAIT state. Actual: %b", mem_req_rd_en);
        
        // Release Waitrequest
        @(posedge clk);
        ddr3_waitrequest = 0;
        #1;
        // Should return to IDLE and assert EN (popping)
        if (mem_req_rd_en !== 1) $error("Core Request NOT accepted (en!=1) after Waitrequest release");
        
        @(posedge clk);
        mem_req_rd_valid = 0;

        #100;
        $display("Test Complete");
        $finish;
    end

endmodule

mem_shim.vcd
$date
	Sat Feb 14 22:58:12 2026
$end
$version
	Icarus Verilog
$end
$timescale
	1ps
$end
$scope module tb_mem_shim $end
$var wire 8 ! ddr3_burstcnt [7:0] $end
$var wire 8 " ddr3_byteenable [7:0] $end
$var wire 1 # mem_res_wr_en $end
$var wire 64 $ mem_res_wr_dta [63:0] $end
$var wire 1 % mem_req_rd_en $end
$var wire 64 & ddr3_writedata [63:0] $end
$var wire 1 ' ddr3_write $end
$var wire 1 ( ddr3_read $end
$var wire 29 ) ddr3_addr [28:0] $end
$var reg 1 * clk $end
$var reg 64 + ddr3_readdata [63:0] $end
$var reg 1 , ddr3_readdatavalid $end
$var reg 1 - ddr3_waitrequest $end
$var reg 22 . mem_req_rd_addr [21:0] $end
$var reg 2 / mem_req_rd_cmd [1:0] $end
$var reg 64 0 mem_req_rd_dta [63:0] $end
$var reg 1 1 mem_req_rd_valid $end
$var reg 1 2 mem_res_wr_almost_full $end
$var reg 1 3 rst_n $end
$scope module uut $end
$var wire 1 * clk $end
$var wire 29 4 ddr3_addr [28:0] $end
$var wire 8 5 ddr3_burstcnt [7:0] $end
$var wire 8 6 ddr3_byteenable [7:0] $end
$var wire 64 7 ddr3_readdata [63:0] $end
$var wire 1 , ddr3_readdatavalid $end
$var wire 1 - ddr3_waitrequest $end
$var wire 64 8 ddr3_writedata [63:0] $end
$var wire 16 9 debug_rd_count [15:0] $end
$var wire 1 : debug_sdram_ack $end
$var wire 1 ; debug_sdram_busy $end
$var wire 16 < debug_wr_count [15:0] $end
$var wire 22 = mem_req_rd_addr [21:0] $end
$var wire 2 > mem_req_rd_cmd [1:0] $end
$var wire 64 ? mem_req_rd_dta [63:0] $end
$var wire 1 1 mem_req_rd_valid $end
$var wire 1 2 mem_res_wr_almost_full $end
$var wire 1 @ rd_accepted $end
$var wire 1 3 rst_n $end
$var wire 1 A wr_accepted $end
$var wire 4 B debug_state [3:0] $end
$var wire 1 ' ddr3_write $end
$var wire 1 ( ddr3_read $end
$var parameter 2 C CMD_NOOP $end
$var parameter 2 D CMD_READ $end
$var parameter 2 E CMD_REFRESH $end
$var parameter 2 F CMD_WRITE $end
$var reg 1 % mem_req_rd_en $end
$var reg 64 G mem_res_wr_dta [63:0] $end
$var reg 1 # mem_res_wr_en $end
$var reg 29 H ram_address [28:0] $end
$var reg 1 ( ram_read $end
$var reg 1 ' ram_write $end
$var reg 64 I ram_writedata [63:0] $end
$var reg 16 J rd_count [15:0] $end
$var reg 1 K state $end
$var reg 16 L wr_count [15:0] $end
$upscope $end
$upscope $end
$enddefinitions $end
$comment Show the parameter values. $end
$dumpall
b11 F
b1 E
b10 D
b0 C
$end
#0
$dumpvars
bx L
xK
bx J
bx I
bx H
bx G
b0x B
xA
x@
b0 ?
b0 >
b0 =
bx <
0;
x:
bx 9
bx 8
b0 7
b11111111 6
b1 5
bx 4
03
02
01
b0 0
b0 /
b0 .
0-
0,
b0 +
0*
bx )
x(
x'
bx &
x%
bx $
x#
b11111111 "
b1 !
$end
#5000
0:
0A
0@
b0 $
b0 G
0#
0%
b0 &
b0 8
b0 I
b0 )
b0 4
b0 H
0'
0(
b0 B
0K
b0 <
b0 L
b0 9
b0 J
1*
#10000
0*
#15000
1*
#20000
0*
13
#25000
1%
1*
#30000
0*
#35000
1*
#40000
0*
11
b1101111010101101101111101110111111001010111111101011101010111110 0
b1101111010101101101111101110111111001010111111101011101010111110 ?
b100100011010001010110 .
b100100011010001010110 =
b11 /
b11 >
#45000
1:
1A
b1101111010101101101111101110111111001010111111101011101010111110 &
b1101111010101101101111101110111111001010111111101011101010111110 8
b1101111010101101101111101110111111001010111111101011101010111110 I
b110100100011010001010110000 )
b110100100011010001010110000 4
b110100100011010001010110000 H
1'
1*
#46000
01
#50000
0*
#55000
0:
0A
b1 <
b1 L
0'
1*
#60000
0*
#65000
1*
#66000
11
b110111100110111101111 .
b110111100110111101111 =
b10 /
b10 >
#70000
0*
#75000
1:
1@
0%
b1 B
1K
b110110111100110111101111000 )
b110110111100110111101111000 4
b110110111100110111101111000 H
1(
1*
#76000
01
#80000
0*
#85000
0:
0@
0(
b1 9
b1 J
1*
#90000
0*
#95000
1*
#96000
1,
b100100011010001010110011110001001101010111100110111101111 +
b100100011010001010110011110001001101010111100110111101111 7
#100000
0*
#105000
0%
b0 B
0K
b100100011010001010110011110001001101010111100110111101111 $
b100100011010001010110011110001001101010111100110111101111 G
1#
1*
#106000
0,
#110000
0*
#115000
1%
0#
1*
#120000
0*
#125000
1*
#126000
11
1;
1-
#130000
0*
#135000
1*
#140000
0*
#145000
1:
1@
0%
b1 B
1K
1(
0;
0-
1*
#150000
0*
#155000
0:
0@
b10 9
b10 J
0(
01
1*
